legacy_web_mcp/__init__.py
legacy_web_mcp/__main__.py
legacy_web_mcp/cli.py
legacy_web_mcp/browser/__init__.py
legacy_web_mcp/browser/analysis.py
legacy_web_mcp/browser/interaction.py
legacy_web_mcp/browser/models.py
legacy_web_mcp/browser/navigation.py
legacy_web_mcp/browser/network.py
legacy_web_mcp/browser/service.py
legacy_web_mcp/browser/session.py
legacy_web_mcp/browser/workflow.py
legacy_web_mcp/config/__init__.py
legacy_web_mcp/config/env_check.py
legacy_web_mcp/config/loader.py
legacy_web_mcp/config/settings.py
legacy_web_mcp/config/validator.py
legacy_web_mcp/discovery/__init__.py
legacy_web_mcp/discovery/crawler.py
legacy_web_mcp/discovery/http.py
legacy_web_mcp/discovery/models.py
legacy_web_mcp/discovery/pipeline.py
legacy_web_mcp/discovery/robots.py
legacy_web_mcp/discovery/sitemap.py
legacy_web_mcp/discovery/utils.py
legacy_web_mcp/documentation/__init__.py
legacy_web_mcp/documentation/assembler.py
legacy_web_mcp/file_management/__init__.py
legacy_web_mcp/file_management/organizer.py
legacy_web_mcp/llm/__init__.py
legacy_web_mcp/llm/artifacts.py
legacy_web_mcp/llm/config_manager.py
legacy_web_mcp/llm/debugging.py
legacy_web_mcp/llm/engine.py
legacy_web_mcp/llm/model_registry.py
legacy_web_mcp/llm/models.py
legacy_web_mcp/llm/quality.py
legacy_web_mcp/llm/utils.py
legacy_web_mcp/llm/analysis/__init__.py
legacy_web_mcp/llm/analysis/step1_summarize.py
legacy_web_mcp/llm/analysis/step2_feature_analysis.py
legacy_web_mcp/llm/prompts/__init__.py
legacy_web_mcp/llm/prompts/step1_summarize.py
legacy_web_mcp/llm/prompts/step2_feature_analysis.py
legacy_web_mcp/llm/providers/__init__.py
legacy_web_mcp/llm/providers/anthropic_provider.py
legacy_web_mcp/llm/providers/gemini_provider.py
legacy_web_mcp/llm/providers/langchain_provider.py
legacy_web_mcp/llm/providers/openai_provider.py
legacy_web_mcp/mcp/__init__.py
legacy_web_mcp/mcp/analysis_tools.py
legacy_web_mcp/mcp/browser_tools.py
legacy_web_mcp/mcp/config_tools.py
legacy_web_mcp/mcp/debugging_tools.py
legacy_web_mcp-0.1.4.dist-info/licenses/LICENSE
legacy_web_mcp-0.1.4.dist-info/METADATA
legacy_web_mcp-0.1.4.dist-info/WHEEL
legacy_web_mcp-0.1.4.dist-info/entry_points.txt
legacy_web_mcp-0.1.4.dist-info/top_level.txt
legacy_web_mcp-0.1.4.dist-info/RECORD
