Metadata-Version: 2.4
Name: legacy-web-mcp
Version: 0.1.4
Summary: AI-powered legacy web application analysis and documentation generation via MCP
Author-email: Legacy Web MCP Team <legacy-web-mcp@example.com>
License-Expression: MIT
Project-URL: Homepage, https://github.com/hieutrtr//web-discovery-mcp
Project-URL: Repository, https://github.com/hieutrtr//web-discovery-mcp
Project-URL: Documentation, https://github.com/hieutrtr/web-discovery-mcp/docs
Project-URL: Issues, https://github.com/hieutrtr//web-discovery-mcp/issues
Keywords: mcp,fastmcp,legacy,web,analysis,ai,automation,documentation
Classifier: Development Status :: 4 - Beta
Classifier: Intended Audience :: Developers
Classifier: Programming Language :: Python :: 3
Classifier: Programming Language :: Python :: 3.11
Classifier: Programming Language :: Python :: 3.12
Classifier: Topic :: Software Development :: Documentation
Classifier: Topic :: Internet :: WWW/HTTP :: Browsers
Classifier: Topic :: Scientific/Engineering :: Artificial Intelligence
Requires-Python: >=3.11
License-File: LICENSE
Requires-Dist: fastmcp==2.12.0
Requires-Dist: playwright==1.55.0
Requires-Dist: aiohttp==3.12.15
Requires-Dist: pydantic-settings==2.10.1
Requires-Dist: structlog==25.4.0
Requires-Dist: pyyaml==6.0.2
Requires-Dist: langchain>=0.3.0
Requires-Dist: langchain-core>=0.3.0
Requires-Dist: langchain-openai>=0.2.0
Requires-Dist: langchain-anthropic>=0.2.0
Requires-Dist: langchain-google-genai>=2.0.0
Requires-Dist: langchain-community>=0.3.0
Provides-Extra: dev
Requires-Dist: ruff==0.13.0; extra == "dev"
Requires-Dist: mypy==1.18.1; extra == "dev"
Requires-Dist: pytest==8.4.2; extra == "dev"
Requires-Dist: pytest-asyncio==1.2.0; extra == "dev"
Requires-Dist: bandit==1.7.9; extra == "dev"
Dynamic: license-file
